perf_analyzer/__init__.py
perf_analyzer/cli.py
perf_analyzer/bin/perf_analyzer
perf_analyzer-2.59.1.dist-info/licenses/LICENSE
perf_analyzer-2.59.1.dist-info/METADATA
perf_analyzer-2.59.1.dist-info/WHEEL
perf_analyzer-2.59.1.dist-info/entry_points.txt
perf_analyzer-2.59.1.dist-info/top_level.txt
perf_analyzer-2.59.1.dist-info/RECORD
