Metadata-Version: 2.4
Name: perf-analyzer
Version: 2.59.1
Summary: Triton Performance Analyzer
License-File: LICENSE
Dynamic: license-file
